{
    "shelf_1": {
		"asset_path_extension": "Assets/ArchVis/Industrial/Shelves/RackLongEmpty_A2.usd",
		"translation": [8.54, 12.7, 0],
        "scale": [0.01, 0.01, 0.01]
	},
    "shelf_2": {
		"asset_path_extension": "Assets/ArchVis/Industrial/Shelves/RackLongEmpty_A2.usd",
		"translation": [8.54, 17.3, 0],
        "scale": [0.01, 0.01, 0.01]
	},
    "shelf_3": {
		"asset_path_extension": "Assets/ArchVis/Industrial/Shelves/RackLongEmpty_A2.usd",
		"translation": [8.54, 27.69, 0],
        "scale": [0.01, 0.01, 0.01]
	},
    "shelf_4": {
		"asset_path_extension": "Assets/ArchVis/Industrial/Shelves/RackLongEmpty_A2.usd",
		"translation": [8.54, 32.3, 0],
        "scale": [0.01, 0.01, 0.01]
	},
    "shelf_5": {
		"asset_path_extension": "Assets/ArchVis/Industrial/Shelves/RackLongEmpty_A2.usd",
		"translation": [14.08, 12.7, 0],
        "scale": [0.01, 0.01, 0.01]
	},
    "shelf_6": {
		"asset_path_extension": "Assets/ArchVis/Industrial/Shelves/RackLongEmpty_A2.usd",
		"translation": [14.08, 17.3, 0],
        "scale": [0.01, 0.01, 0.01]
	},
    "shelf_7": {
		"asset_path_extension": "Assets/ArchVis/Industrial/Shelves/RackLongEmpty_A2.usd",
		"translation": [14.08, 27.69, 0],
        "scale": [0.01, 0.01, 0.01]
	},
    "shelf_8": {
		"asset_path_extension": "Assets/ArchVis/Industrial/Shelves/RackLongEmpty_A2.usd",
		"translation": [14.08, 32.3, 0],
        "scale": [0.01, 0.01, 0.01]
	},
    "shelf_9": {
		"asset_path_extension": "Assets/ArchVis/Industrial/Shelves/RackLongEmpty_A2.usd",
		"translation": [15.13, 12.7, 0],
        "scale": [0.01, 0.01, 0.01]
	},
    "shelf_10": {
		"asset_path_extension": "Assets/ArchVis/Industrial/Shelves/RackLongEmpty_A2.usd",
		"translation": [15.13, 17.3, 0],
        "scale": [0.01, 0.01, 0.01]
	},
    "shelf_11": {
		"asset_path_extension": "Assets/ArchVis/Industrial/Shelves/RackLongEmpty_A2.usd",
		"translation": [15.13, 27.69, 0],
        "scale": [0.01, 0.01, 0.01]
	},
    "shelf_12": {
		"asset_path_extension": "Assets/ArchVis/Industrial/Shelves/RackLongEmpty_A2.usd",
		"translation": [15.13, 32.3, 0],
        "scale": [0.01, 0.01, 0.01]
	},
    "shelf_13": {
		"asset_path_extension": "Assets/ArchVis/Industrial/Shelves/RackLongEmpty_A2.usd",
		"translation": [20.81, 12.7, 0],
        "scale": [0.01, 0.01, 0.01]
	},
    "shelf_14": {
		"asset_path_extension": "Assets/ArchVis/Industrial/Shelves/RackLongEmpty_A2.usd",
		"translation": [20.81, 17.3, 0],
        "scale": [0.01, 0.01, 0.01]
	},
    "shelf_15": {
		"asset_path_extension": "Assets/ArchVis/Industrial/Shelves/RackLongEmpty_A2.usd",
		"translation": [20.81, 27.69, 0],
        "scale": [0.01, 0.01, 0.01]
	},
    "shelf_16": {
		"asset_path_extension": "Assets/ArchVis/Industrial/Shelves/RackLongEmpty_A2.usd",
		"translation": [20.81, 32.3, 0],
        "scale": [0.01, 0.01, 0.01]
	},
    "shelf_17": {
		"asset_path_extension": "Assets/ArchVis/Industrial/Shelves/RackLongEmpty_A2.usd",
		"translation": [21.86, 12.7, 0],
        "scale": [0.01, 0.01, 0.01]
	},
    "shelf_18": {
		"asset_path_extension": "Assets/ArchVis/Industrial/Shelves/RackLongEmpty_A2.usd",
		"translation": [21.86, 17.3, 0],
        "scale": [0.01, 0.01, 0.01]
	},
    "shelf_19": {
		"asset_path_extension": "Assets/ArchVis/Industrial/Shelves/RackLongEmpty_A2.usd",
		"translation": [21.86, 27.69, 0],
        "scale": [0.01, 0.01, 0.01]
	},
    "shelf_20": {
		"asset_path_extension": "Assets/ArchVis/Industrial/Shelves/RackLongEmpty_A2.usd",
		"translation": [21.86, 32.3, 0],
        "scale": [0.01, 0.01, 0.01]
	},
    "shelf_21": {
		"asset_path_extension": "Assets/ArchVis/Industrial/Shelves/RackLongEmpty_A2.usd",
		"translation": [27.46, 12.7, 0],
        "scale": [0.01, 0.01, 0.01]
	},
    "shelf_22": {
		"asset_path_extension": "Assets/ArchVis/Industrial/Shelves/RackLongEmpty_A2.usd",
		"translation": [27.46, 17.3, 0],
        "scale": [0.01, 0.01, 0.01]
	},
    "shelf_23": {
		"asset_path_extension": "Assets/ArchVis/Industrial/Shelves/RackLongEmpty_A2.usd",
		"translation": [27.46, 27.69, 0],
        "scale": [0.01, 0.01, 0.01]
	},
    "shelf_24": {
		"asset_path_extension": "Assets/ArchVis/Industrial/Shelves/RackLongEmpty_A2.usd",
		"translation": [27.46, 32.3, 0],
        "scale": [0.01, 0.01, 0.01]
	}
}